iccore/__init__.py
iccore/base_models.py
iccore/cli_utils.py
iccore/dict_utils.py
iccore/logging_utils.py
iccore/main_cli.py
iccore/py.typed
iccore/runtime.py
iccore/string_utils.py
iccore/tags.py
iccore/test_utils.py
iccore/time_utils.py
iccore/url_utils.py
iccore/auth/__init__.py
iccore/auth/user.py
iccore/data/__init__.py
iccore/data/array.py
iccore/data/dataset.py
iccore/data/measurement.py
iccore/data/model.py
iccore/data/product.py
iccore/data/series.py
iccore/data/source.py
iccore/data/units.json
iccore/data/units.py
iccore/database/__init__.py
iccore/database/database.py
iccore/database/models.py
iccore/filesystem/__init__.py
iccore/filesystem/cli.py
iccore/filesystem/filesystem.py
iccore/network/__init__.py
iccore/network/cli.py
iccore/network/http_client.py
iccore/serialization/__init__.py
iccore/serialization/csv_utils.py
iccore/serialization/json_utils.py
iccore/serialization/key_value.py
iccore/serialization/yaml_utils.py
iccore/system/__init__.py
iccore/system/cpu.py
iccore/system/environment.py
iccore/system/gpu.py
iccore/system/process.py
iccore/system/system_event.py
iccore/system/cluster/__init__.py
iccore/system/cluster/cluster_allocation.py
iccore/system/cluster/node.py
iccore/system/network/__init__.py
iccore/system/network/host.py
iccore/system/network/info.py
iccore-0.2.6.dist-info/licenses/LICENSE.txt
iccore-0.2.6.dist-info/METADATA
iccore-0.2.6.dist-info/WHEEL
iccore-0.2.6.dist-info/entry_points.txt
iccore-0.2.6.dist-info/top_level.txt
iccore-0.2.6.dist-info/RECORD
