Metadata-Version: 2.4
Name: iccore
Version: 0.2.6
Summary: A collection of common data structures and utilities used in other ICHEC tools
Author-email: "James Grogan, Irish Centre for High End Computing" <james.grogan@ichec.ie>
Project-URL: Repository, https://git.ichec.ie/performance/toolshed/iccore
Project-URL: Homepage, https://git.ichec.ie/performance/toolshed/iccore
Keywords: HPC
Classifier: Development Status :: 3 - Alpha
Classifier: Programming Language :: Python :: 3
Classifier: License :: OSI Approved :: GNU General Public License v3 or later (GPLv3+)
Classifier: Operating System :: OS Independent
Classifier: Topic :: System :: Distributed Computing
Requires-Python: >=3.10
License-File: LICENSE.txt
Requires-Dist: PyYAML
Requires-Dist: sqlmodel
Requires-Dist: numpy
Provides-Extra: test
Requires-Dist: pytest; extra == "test"
Requires-Dist: pytest-cov; extra == "test"
Requires-Dist: pytest-sugar; extra == "test"
Requires-Dist: pytest-mock; extra == "test"
Requires-Dist: black; extra == "test"
Requires-Dist: mypy; extra == "test"
Requires-Dist: flake8; extra == "test"
Requires-Dist: pylint; extra == "test"
Provides-Extra: types
Requires-Dist: types-PyYAML; extra == "types"
Dynamic: license-file
